{
	"sales-pitch": "Svar. Helt. Enkelt.",
	"invite": "Bjud in deltagare med den här länken:",
	"createPoll": "Skapa röstning",
	"participatePoll": "Delta i röstning",
	"question": "Fråga",
	"changeLanguage": "Change to English",
	"createButton": "SKAPA",
	"playButton": "SPELA",
	"createHeader": "Skapa ditt quiz",
	"word": "Ord",
    "translation": "Översättning",
    "addWord": "Lägg till ord",
    "removeWord": "Ta bort ord",
    "saveQuiz":  "Spara quiz",
	"answer": "Svar",
	"flashcard": "Flashcard",
	"submit": "Skicka in",
	"nameQuiz": "Namnge ditt quiz",
	"name": "Namnge ditt quiz",
	"playHeader": "Quizbibliotek",
	"usernameQuiz": "Ange ditt användarnamn",
	"username": "Användarnamn",
	"play": "Starta",
    "edit": "Redigera",
    "delete": "Radera",
	"createNewQuiz": "Skapa nytt quiz",
	"nextQuestion": "Nästa fråga",
	"done": "Klar",
	"finalResultHeader": "Topplista",
	"myResultHeader": "Mitt resultat",
	"endQuiz": "Avsluta quiz",
	"tryAgain": "Försök igen",
	"joinQuiz": "Gå med i quiz",
	"quizID": "Quiz ID",
	"waiting": "Väntar på att spelet ska starta..."
}